simple_remote_function_call/__init__.py
simple_remote_function_call/client.py
simple_remote_function_call/globals.py
simple_remote_function_call/wsgi.py
simple_remote_function_call-0.1.dist-info/METADATA
simple_remote_function_call-0.1.dist-info/WHEEL
simple_remote_function_call-0.1.dist-info/entry_points.txt
simple_remote_function_call-0.1.dist-info/top_level.txt
simple_remote_function_call-0.1.dist-info/RECORD
